APOExptime/APOinputclasses.py
APOExptime/Plotter.py
APOExptime/__init__.py
APOExptime/data/Sky/moon_00.txt
APOExptime/data/Sky/moon_100.txt
APOExptime/data/Sky/moon_50.txt
APOExptime/data/Sky/trans_1.txt
APOExptime/data/Sky/trans_1_5.txt
APOExptime/data/Sky/trans_2.txt
APOExptime/data/Sky/trans_2_5.txt
APOExptime/data/apo3_5m/al_reflectivity.dat
APOExptime/data/apo3_5m/Agile/Agile_qe.txt
APOExptime/data/apo3_5m/Agile/fov.data
APOExptime/data/apo3_5m/Agile/gain.data
APOExptime/data/apo3_5m/Agile/pix_size.data
APOExptime/data/apo3_5m/Agile/platescale.data
APOExptime/data/apo3_5m/Agile/qe.data
APOExptime/data/apo3_5m/Agile/readme.txt
APOExptime/data/apo3_5m/Agile/rn.data
APOExptime/data/apo3_5m/Arces/Arces_default_disp.data
APOExptime/data/apo3_5m/Arces/Arces_default_effic.data
APOExptime/data/apo3_5m/Arces/Arces_default_qe.data
APOExptime/data/apo3_5m/Arces/Arces_param.yaml
APOExptime/data/apo3_5m/Arctic/Arctic_param.yaml
APOExptime/data/apo3_5m/Arctic/Arctic_qe.data
APOExptime/data/apo3_5m/Arctic/gprime_filter.data
APOExptime/data/apo3_5m/Arctic/iprime_filter.data
APOExptime/data/apo3_5m/Arctic/readme.txt
APOExptime/data/apo3_5m/Arctic/rprime_filter.data
APOExptime/data/apo3_5m/Arctic/uprime_filter.data
APOExptime/data/apo3_5m/Arctic/zprime_filter.data
APOExptime/data/apo3_5m/DIS/DIS_B1200_disp.data
APOExptime/data/apo3_5m/DIS/DIS_B1200_effic.data
APOExptime/data/apo3_5m/DIS/DIS_B400_disp.data
APOExptime/data/apo3_5m/DIS/DIS_B400_effic.data
APOExptime/data/apo3_5m/DIS/DIS_Blue_qe.data
APOExptime/data/apo3_5m/DIS/DIS_R1200_disp.data
APOExptime/data/apo3_5m/DIS/DIS_R1200_effic.data
APOExptime/data/apo3_5m/DIS/DIS_R300_disp.data
APOExptime/data/apo3_5m/DIS/DIS_R300_effic.data
APOExptime/data/apo3_5m/DIS/DIS_R830_disp.data
APOExptime/data/apo3_5m/DIS/DIS_R830_effic.data
APOExptime/data/apo3_5m/DIS/DIS_Red_qe.data
APOExptime/data/apo3_5m/DIS/DIS_param.yaml
APOExptime/data/apo3_5m/NICFPS/NICFPS_param.yaml
APOExptime/data/apo3_5m/NICFPS/NICFPS_qe.data
APOExptime-2.3.dist-info/LICENSE.txt
APOExptime-2.3.dist-info/METADATA
APOExptime-2.3.dist-info/WHEEL
APOExptime-2.3.dist-info/top_level.txt
APOExptime-2.3.dist-info/RECORD
